formator/__init__.py
formator/viewJson.py
formator-0.1.1.dist-info/licenses/LICENSE
formator-0.1.1.dist-info/METADATA
formator-0.1.1.dist-info/WHEEL
formator-0.1.1.dist-info/top_level.txt
formator-0.1.1.dist-info/RECORD
