Metadata-Version: 2.4
Name: formator
Version: 0.1.1
Summary: A package for formatting dict, list, tuple, etc.
Home-page: https://github.com/yourname/mygreatpkg
Author: Oracle Yuan
Author-email: youremail@example.com
Classifier: Programming Language :: Python :: 3
Classifier: License :: OSI Approved :: MIT License
Classifier: Operating System :: OS Independent
Requires-Python: >=3.7
License-File: LICENSE
Dynamic: author
Dynamic: author-email
Dynamic: classifier
Dynamic: description-content-type
Dynamic: home-page
Dynamic: license-file
Dynamic: requires-python
Dynamic: summary
